{"actions":[{"Edit":{"files_to_add":[{"region_id":4398046511104,"file_id":"3b464f6d-fe03-470d-8793-a2e06ccc72c3","time_range":[{"value":1739610967075,"unit":"Millisecond"},{"value":1739611389555,"unit":"Millisecond"}],"level":0,"file_size":37260,"available_indexes":["InvertedIndex"],"index_file_size":14189,"num_rows":21276,"num_row_groups":1,"sequence":133725},{"region_id":4398046511104,"file_id":"b87eb50b-edd7-4095-be6a-8f043812f0c4","time_range":[{"value":1739778262075,"unit":"Millisecond"},{"value":1739779191621,"unit":"Millisecond"}],"level":0,"file_size":52498,"available_indexes":["InvertedIndex"],"index_file_size":16725,"num_rows":36850,"num_row_groups":1,"sequence":170575},{"region_id":4398046511104,"file_id":"6861d92d-923a-4e27-9b9d-1d3222d58b0b","time_range":[{"value":1739779206279,"unit":"Millisecond"},{"value":1739780901621,"unit":"Millisecond"}],"level":0,"file_size":80532,"available_indexes":["InvertedIndex"],"index_file_size":24510,"num_rows":84360,"num_row_groups":1,"sequence":254935}],"files_to_remove":[],"compaction_time_window":null,"flushed_entry_id":2069,"flushed_sequence":254935}}]}